azsecrets/__init__.py
azsecrets-2.0.1.dist-info/LICENSE
azsecrets-2.0.1.dist-info/METADATA
azsecrets-2.0.1.dist-info/WHEEL
azsecrets-2.0.1.dist-info/entry_points.txt
azsecrets-2.0.1.dist-info/top_level.txt
azsecrets-2.0.1.dist-info/RECORD
