Metadata-Version: 2.1
Name: azsecrets
Version: 2.0.1
Summary: Set Azure Secrets as environment variables.
Home-page: https://github.com/akshaybabloo/azsecrets
Author: Akshay Raj Gollahalli
Author-email: akshay@gollahalli.com
License: MIT
Keywords: azure,secrets
Platform: UNKNOWN
Classifier: License :: OSI Approved :: MIT License
Classifier: Programming Language :: Python :: 3 :: Only
Classifier: Programming Language :: Python :: 3.5
Classifier: Programming Language :: Python :: 3.6
Classifier: Programming Language :: Python :: 3.7
Classifier: Programming Language :: Python :: 3.8
Classifier: Intended Audience :: Developers
Classifier: Environment :: Console
Classifier: Development Status :: 5 - Production/Stable
Classifier: Topic :: Utilities
Requires-Dist: click (==7.0)
Requires-Dist: azure-keyvault-secrets (==4.0.0)
Requires-Dist: azure-identity (==1.2.0)
